vineyard/contrib/kedro/__init__.py
vineyard/contrib/kedro/io/__init__.py
vineyard/contrib/kedro/io/dataset.py
vineyard/contrib/kedro/plugins/__init__.py
vineyard/contrib/kedro/plugins/argo.py
vineyard/contrib/kedro/plugins/catalog.py
vineyard/contrib/kedro/plugins/cli.py
vineyard/contrib/kedro/plugins/docker.py
vineyard/contrib/kedro/plugins/hook.py
vineyard/contrib/kedro/plugins/starter.py
vineyard/contrib/kedro/plugins/templates/Dockerfile.tmpl
vineyard/contrib/kedro/plugins/templates/argo_spec.tmpl
vineyard/contrib/kedro/runner/__init__.py
vineyard/contrib/kedro/runner/parallel_runner.py
vineyard/contrib/kedro/runner/sequential_runner.py
vineyard/contrib/kedro/runner/thread_runner.py
vineyard_kedro-0.24.2.dist-info/LICENSE
vineyard_kedro-0.24.2.dist-info/METADATA
vineyard_kedro-0.24.2.dist-info/NOTICE.txt
vineyard_kedro-0.24.2.dist-info/WHEEL
vineyard_kedro-0.24.2.dist-info/entry_points.txt
vineyard_kedro-0.24.2.dist-info/top_level.txt
vineyard_kedro-0.24.2.dist-info/RECORD
